ashutosh/__init__.py
ashutosh/maths_utils.py
ashutosh/strings_utils.py
ashutosh-1.0.0.dist-info/METADATA
ashutosh-1.0.0.dist-info/WHEEL
ashutosh-1.0.0.dist-info/top_level.txt
ashutosh-1.0.0.dist-info/RECORD
