Metadata-Version: 2.1
Name: ashutosh
Version: 1.0.0
Summary: A simple demo package with math and string utilities
Author: Ashutosh
